Metadata-Version: 2.1
Name: pycircpl
Version: 1.0
Summary: Python logic circuit programming language
Home-page: https://www.samyzaf.com/pycircpl/pycircpl.html
Author: Samy Zafrany
Author-email: sz@samyzaf.com
License: MIT
Keywords: logic circuit programming language
Platform: UNKNOWN
